utilities/__init__.py
utilities/shell_utils.py
zoe_utils-0.1.2.dist-info/LICENSE
zoe_utils-0.1.2.dist-info/METADATA
zoe_utils-0.1.2.dist-info/WHEEL
zoe_utils-0.1.2.dist-info/top_level.txt
zoe_utils-0.1.2.dist-info/RECORD
