Metadata-Version: 2.1
Name: zoe-utils
Version: 0.1.2
Summary: A Zeo utility library for working with Prefect
Home-page: https://github.com/pavlo-sevidov-datavise/zoe-utils
Author: Pavlo Sevidov
Author-email: pavlo.sevidov@datavise.ai
License: MIT
Classifier: Programming Language :: Python :: 3
Classifier: License :: OSI Approved :: MIT License
Classifier: Operating System :: OS Independent
Requires-Python: >=3.11
License-File: LICENSE
